piholelongtermstats/__init__.py
piholelongtermstats/app.py
piholelongtermstats/db.py
piholelongtermstats/plot.py
piholelongtermstats/process.py
piholelongtermstats/stats.py
piholelongtermstats/assets/favicon.ico
piholelongtermstats/assets/logo_phlts.png
piholelongtermstats/assets/style.css
piholelongtermstats-0.2.2.dist-info/licenses/LICENSE
piholelongtermstats-0.2.2.dist-info/METADATA
piholelongtermstats-0.2.2.dist-info/WHEEL
piholelongtermstats-0.2.2.dist-info/entry_points.txt
piholelongtermstats-0.2.2.dist-info/top_level.txt
piholelongtermstats-0.2.2.dist-info/RECORD
