Metadata-Version: 2.4
Name: piholelongtermstats
Version: 0.2.2
Summary: A dashboard to explore long-term DNS query data from Pi-hole FTL database files.
Author-email: Davis Thomas Daniel <davisthomasdaniel@gmail.com>
Maintainer-email: Davis Thomas Daniel <davisthomasdaniel@gmail.com>
License-Expression: MIT
Project-URL: Homepage, https://github.com/davistdaniel/PiHoleLongTermStats
Project-URL: Documentation, https://github.com/davistdaniel/PiHoleLongTermStats
Project-URL: Repository, https://github.com/davistdaniel/PiHoleLongTermStats.git
Project-URL: Bug Tracker, https://github.com/davistdaniel/PiHoleLongTermStats/issues
Keywords: dashboard,pihole,visualization,plotly,dash
Classifier: Programming Language :: Python
Requires-Python: >=3.11
License-File: LICENSE
Requires-Dist: dash==3.0.4
Requires-Dist: pandas==2.2.3
Requires-Dist: plotly==6.0.1
Requires-Dist: psutil==7.1.2
Provides-Extra: develop
Requires-Dist: pytest==9.0.1; extra == "develop"
Requires-Dist: ruff; extra == "develop"
Requires-Dist: build==1.3.0; extra == "develop"
Requires-Dist: twine==6.2.0; extra == "develop"
Requires-Dist: pytest-cov==7.0.0; extra == "develop"
Dynamic: license-file
